{
    "python-Attest": "-",
    "python-Babel-doc": "-",
    "python-WebOb-doc": "-",
    "python-WebTest-doc": "-",
    "python-Werkzeug-doc": "-",
    "python-amqp-doc": "-",
    "python-apsw": "3.9.2-r1",
    "python-beautifulsoup4-doc": "-",
    "python-boto-doc": "-",
    "python-cffi-doc": "-",
    "python-greenlet-doc": "-",
    "python-irc": "-",
    "python-jupyter_client-doc": "-",
    "python-jupyter_console-doc": "-",
    "python-jupyter_core-doc": "-",
    "python-jupyter_ipykernel-doc": "-",
    "python-jupyter_ipyparallel-doc": "-",
    "python-jupyter_ipython-doc": "-",
    "python-jupyter_ipywidgets-doc": "-",
    "python-jupyter_nbformat-doc": "-",
    "python-jupyter_notebook-doc": "-",
    "python-jupyter_qtconsole-doc": "-",
    "python-keyrings.alt": "-",
    "python-louis": "-",
    "python-matplotib": "2.1.0",
    "python-mock-doc": "-",
    "python-numpy-doc": "-",
    "python-pandas-doc": "-",
    "python-pbr-doc": "-",
    "python-pep8": "-",
    "python-persistent-doc": "-",
    "python-pluggy03": "-",
    "python-polib-doc": "-",
    "python-psycopg2-doc": "-",
    "python-py-doc": "-",
    "python-pyOpenSSL-doc": "-",
    "python-pyramid-doc": "-",
    "python-pyramid_debugtoolbar-doc": "-",
    "python-pyramid_tm-doc": "-",
    "python-pyserial-doc": "-",
    "python-pytest-doc": "-",
    "python-rarfile-doc": "-",
    "python-testtools-doc": "-",
    "python-tox-doc": "-",
    "python-virtualenv-doc": "-",
    "python-xlwt-doc": "-",
    "python-zope.component-doc": "-",
    "python-zope.deprecation-doc": "-"
}